lalamo/__init__.py
lalamo/commands.py
lalamo/common.py
lalamo/main.py
lalamo/message_processor.py
lalamo/quantization.py
lalamo/registry_abc.py
lalamo/safetensors.py
lalamo/sampling.py
lalamo/utils.py
lalamo/data/__init__.py
lalamo/data/huggingface_message.py
lalamo/data/lalamo_completions.py
lalamo/data/utils.py
lalamo/model_import/__init__.py
lalamo/model_import/common.py
lalamo/model_import/huggingface_generation_config.py
lalamo/model_import/huggingface_tokenizer_config.py
lalamo/model_import/decoder_configs/__init__.py
lalamo/model_import/decoder_configs/common.py
lalamo/model_import/decoder_configs/executorch.py
lalamo/model_import/decoder_configs/huggingface/__init__.py
lalamo/model_import/decoder_configs/huggingface/common.py
lalamo/model_import/decoder_configs/huggingface/gemma2.py
lalamo/model_import/decoder_configs/huggingface/gemma3.py
lalamo/model_import/decoder_configs/huggingface/gpt_oss.py
lalamo/model_import/decoder_configs/huggingface/lfm2.py
lalamo/model_import/decoder_configs/huggingface/llama.py
lalamo/model_import/decoder_configs/huggingface/llamba.py
lalamo/model_import/decoder_configs/huggingface/mistral.py
lalamo/model_import/decoder_configs/huggingface/modern_bert.py
lalamo/model_import/decoder_configs/huggingface/qwen2.py
lalamo/model_import/decoder_configs/huggingface/qwen3.py
lalamo/model_import/loaders/__init__.py
lalamo/model_import/loaders/common.py
lalamo/model_import/loaders/executorch.py
lalamo/model_import/loaders/huggingface.py
lalamo/model_import/loaders/utils.py
lalamo/model_import/model_specs/__init__.py
lalamo/model_import/model_specs/common.py
lalamo/model_import/model_specs/deepseek.py
lalamo/model_import/model_specs/essential_ai.py
lalamo/model_import/model_specs/gemma.py
lalamo/model_import/model_specs/gpt_oss.py
lalamo/model_import/model_specs/huggingface.py
lalamo/model_import/model_specs/lfm2.py
lalamo/model_import/model_specs/llama.py
lalamo/model_import/model_specs/llamba.py
lalamo/model_import/model_specs/mirai.py
lalamo-0.5.17.dist-info/licenses/LICENSE
lalamo-0.5.17.dist-info/METADATA
lalamo-0.5.17.dist-info/WHEEL
lalamo-0.5.17.dist-info/entry_points.txt
lalamo-0.5.17.dist-info/top_level.txt
lalamo-0.5.17.dist-info/RECORD
