Metadata-Version: 2.4
Name: lalamo
Version: 0.5.17
Summary: JAX library for optimization and export of models for use with the UZU inference engine.
Requires-Python: <4,>=3.12
License-File: LICENSE
Requires-Dist: cattrs[msgpack]>=24.1.2
Requires-Dist: click>=8.1.8
Requires-Dist: einops>=0.8.0
Requires-Dist: equinox>=0.11.11
Requires-Dist: huggingface-hub[hf-transfer]>=0.27.1
Requires-Dist: jax>=0.8.1
Requires-Dist: jaxtyping>=0.2.36
Requires-Dist: jinja2>=3.1.6
Requires-Dist: ml-dtypes>=0.5.1
Requires-Dist: optax>=0.2.4
Requires-Dist: rich>=14.0.0
Requires-Dist: thefuzz>=0.22.1
Requires-Dist: tokenizers>=0.21.2
Requires-Dist: typer>=0.15.1
Requires-Dist: polars>=1.33.1
Requires-Dist: xxhash>=3.5.0
Provides-Extra: cpu
Requires-Dist: jax[cpu]>=0.8.1; extra == "cpu"
Provides-Extra: cuda
Requires-Dist: jax[cuda]>=0.8.1; extra == "cuda"
Provides-Extra: tpu
Requires-Dist: jax[tpu]>=0.8.1; extra == "tpu"
Dynamic: license-file
